{"0": "affirm", "1": "ashwagandha", "2": "ask_drug_info", "3": "ask_reproductive_health", "4": "bot_challenge", "5": "common_causes", "6": "d_aspartic_acid_supplements", "7": "day", "8": "deny", "9": "dietary_changes_affect_healthy_eggs", "10": "egg_quality_important", "11": "enhance_quality_eggs", "12": "fenugreek_supplements", "13": "flu_symptom", "14": "food_increase_sperm_count", "15": "foods_for_healthy_eggs", "16": "foods_to_avoid_improve_egg_quality", "17": "goodbye", "18": "greet", "19": "head_crown", "20": "head_eyes", "21": "head_sides", "22": "head_symptom", "23": "head_whole", "24": "healthy_avocados_eggs", "25": "healthy_beans_eggs", "26": "healthy_berries_eggs", "27": "healthy_cinnamon_eggs", "28": "healthy_dairy_eggs", "29": "healthy_eggs", "30": "healthy_ginger_eggs", "31": "healthy_green_leafy_eggs", "32": "healthy_nuts_eggs", "33": "healthy_seeds_eggs", "34": "healthy_whole_grains_eggs", "35": "inform", "36": "itchy_testicles", "37": "lifestyle_men", "38": "log_menstrual_cycle", "39": "maca_root", "40": "mood_answer", "41": "mood_unhappy", "42": "organic_non_organic_foods_eggs", "43": "poor_quality_eggs", "44": "sperm_health", "45": "stomach_symptom", "46": "top_ten_diet_rules", "47": "tribulus_terrestris", "48": "vision_symptom", "49": "ways_increase_sperm_count"}