{"0": "affirm", "1": "ask_drug_info", "2": "ask_reproductive_health", "3": "bot_challenge", "4": "common_causes", "5": "day", "6": "deny", "7": "dietary_changes_affect_healthy_eggs", "8": "enhance_quality_eggs", "9": "flu_symptom", "10": "foods_for_healthy_eggs", "11": "foods_to_avoid_improve_egg_quality", "12": "goodbye", "13": "greet", "14": "head_crown", "15": "head_eyes", "16": "head_sides", "17": "head_symptom", "18": "head_whole", "19": "healthy_avocados_eggs", "20": "healthy_beans_eggs", "21": "healthy_berries_eggs", "22": "healthy_cinnamon_eggs", "23": "healthy_dairy_eggs", "24": "healthy_eggs", "25": "healthy_ginger_eggs", "26": "healthy_green_leafy_eggs", "27": "healthy_nuts_eggs", "28": "healthy_seeds_eggs", "29": "healthy_whole_grains_eggs", "30": "inform", "31": "itchy_testicles", "32": "lifestyle_men", "33": "log_menstrual_cycle", "34": "mood_answer", "35": "mood_unhappy", "36": "organic_non_organic_foods_eggs", "37": "poor_quality_eggs", "38": "sperm_health", "39": "stomach_symptom", "40": "vision_symptom"}